Workbook

Sheet Equipment Quotation
A1: RAKSHA (TUK-TUK) REPAIR & TRAINING CENTER
A2: Full Budget Quotation & Equipment Requirement List | Currency: USD ($)
A4: Category | B4: Item Description | C4: Priority | D4: Qty | E4: Unit Price ($) | F4: Total ($) | G4: Function or Purpose
A5: Hand Tools & General Tool Kits | B5: 100-Piece Mechanic Tool Set (Sockets, Ratchets, Spanners, Screwdrivers) | C5: Must-Have | D5: 2 | E5: 120 | F5: =D5*E5 | G5: Complete foundational kit for general motor assembly, body panels, and engine teardown.
A6: Hand Tools & General Tool Kits | B6: Combination Spanner Set (Metric 8mm - 24mm) | C6: Must-Have | D6: 2 | E6: 35 | F6: =D6*E6 | G6: Heavy-duty open and ring spanners for chassis, axle bolts, and engine frame mounts.
A7: Hand Tools & General Tool Kits | B7: Adjustable Wrench Set (8", 10", 12") | C7: Must-Have | D7: 2 | E7: 25 | F7: =D7*E7 | G7: Versatile gripping/turning tool for oversized, square, or non-standard nuts and fittings.
A8: Hand Tools & General Tool Kits | B8: Heavy-Duty Screwdriver Set (Flathead & Phillips) | C8: Must-Have | D8: 2 | E8: 20 | F8: =D8*E8 | G8: For carburetor tuning, body covers, light assemblies, and electrical switch terminals.
A9: Hand Tools & General Tool Kits | B9: Pliers Set (Combination, Long Nose, Water Pump) | C9: Must-Have | D9: 2 | E9: 22 | F9: =D9*E9 | G9: Gripping components, bending safety pins, pulling control cables, and wire work.
A10: Hand Tools & General Tool Kits | B10: Allen / Hex Wrench Key Set (Metric 1.5mm - 10mm) | C10: Must-Have | D10: 2 | E10: 12 | F10: =D10*E10 | G10: Removing internal hex bolts on engine head covers, brake levers, and handlebar clamps.
A11: Engine & Mechanical Specialized Tools | B11: Spark Plug Socket Spanner (16mm & 21mm with T-Bar) | C11: Must-Have | D11: 3 | E11: 8 | F11: =D11*E11 | G11: Safe removal and replacement of spark plugs without cracking ceramic insulation.
A12: Engine & Mechanical Specialized Tools | B12: Feeler Gauge Blade Set (Metric 0.02mm - 1.00mm) | C12: Must-Have | D12: 2 | E12: 10 | F12: =D12*E12 | G12: Measuring precise engine valve (tappet) clearances and spark plug electrode gaps.
A13: Engine & Mechanical Specialized Tools | B13: Circlip / Snap Ring Pliers Set (Internal & External) | C13: Must-Have | D13: 2 | E13: 18 | F13: =D13*E13 | G13: Removing retaining rings in gearboxes, wheel hubs, clutches, and brake pistons.
A14: Engine & Mechanical Specialized Tools | B14: Drive Chain Breaker & Repair Tool | C14: Secondary | D14: 1 | E14: 25 | F14: =D14*E14 | G14: Sizing, removing, and installing drive chains safely on chain-driven Rakshas.
A15: Engine & Mechanical Specialized Tools | B15: Oil Filter Wrench / Strap Removal Tool | C15: Must-Have | D15: 2 | E15: 12 | F15: =D15*E15 | G15: Removing spin-on oil filters during scheduled engine maintenance.
A16: Engine & Mechanical Specialized Tools | B16: Torque Wrench (1/2" Drive, 20-150 ft-lb) | C16: Secondary | D16: 1 | E16: 65 | F16: =D16*E16 | G16: Tightening engine cylinder head bolts and wheel axle nuts to precise safety torque spec.
... A29: Startup Vehicle & Training Assets | B29: Initial Workshop Consumables (Oil, Fluids, Solvents, Parts) | C29: Must-Have | D29: 1 | E29: 150 | F29: =D29*E29 | G29: 4T engine oil, gear oil, brake fluid, grease, spark plugs, patch kits, and shop towels.
A30: GRAND TOTAL (ALL ITEMS) | F30: =SUM(F5:F29)

Sheet Budget Summary
A1: RAKSHA TRAINING CENTER - FINANCIAL SUMMARY
A2: Cost Breakdown by Priority & Category
A4: Priority Level | B4: Item Count | C4: Total Cost ($) | D4: % of Total
A5: Must-Have / Essential Startup | B5: =COUNTIF('Equipment Quotation'!C5:C29, "Must-Have") | C5: =SUMIF('Equipment Quotation'!C5:C29, "Must-Have", 'Equipment Quotation'!F5:F29) | D5: =C5/$C$7
A6: Secondary / Expansion Tools | B6: =COUNTIF('Equipment Quotation'!C5:C29, "Secondary") | C6: =SUMIF('Equipment Quotation'!C5:C29, "Secondary", 'Equipment Quotation'!F5:F29) | D6: =C6/$C$7
A7: Total Startup Investment | B7: =SUM(B5:B6) | C7: =SUM(C5:C6) | D7: =SUM(D5:D6)
A10: Category Breakdown | B10: Must-Have ($) | C10: Secondary ($) | D10: Category Total ($)
A11: Hand Tools & General Tool Kits | B11: =SUMIFS('Equipment Quotation'!F5:F29, 'Equipment Quotation'!A5:A29, A11, 'Equipment Quotation'!C5:C29, "Must-Have") | C11: =SUMIFS('Equipment Quotation'!F5:F29, 'Equipment Quotation'!A5:A29, A11, 'Equipment Quotation'!C5:C29, "Secondary") | D11: =SUM(B11:C11)
A12: Engine & Mechanical Specialized Tools | B12: =SUMIFS('Equipment Quotation'!F5:F29, 'Equipment Quotation'!A5:A29, A12, 'Equipment Quotation'!C5:C29, "Must-Have") | C12: =SUMIFS('Equipment Quotation'!F5:F29, 'Equipment Quotation'!A5:A29, A12, 'Equipment Quotation'!C5:C29, "Secondary") | D12: =SUM(B12:C12)
A13: Brake, Wheel & Suspension Tools | B13: =SUMIFS('Equipment Quotation'!F5:F29, 'Equipment Quotation'!A5:A29, A13, 'Equipment Quotation'!C5:C29, "Must-Have") | C13: =SUMIFS('Equipment Quotation'!F5:F29, 'Equipment Quotation'!A5:A29, A13, 'Equipment Quotation'!C5:C29, "Secondary") | D13: =SUM(B13:C13)
A14: Electrical & Fuel System Diagnostics | B14: =SUMIFS('Equipment Quotation'!F5:F29, 'Equipment Quotation'!A5:A29, A14, 'Equipment Quotation'!C5:C29, "Must-Have") | C14: =SUMIFS('Equipment Quotation'!F5:F29, 'Equipment Quotation'!A5:A29, A14, 'Equipment Quotation'!C5:C29, "Secondary") | D14: =SUM(B14:C14)
A15: Workshop Lifting & Maintenance Equipment | B15: =SUMIFS('Equipment Quotation'!F5:F29, 'Equipment Quotation'!A5:A29, A15, 'Equipment Quotation'!C5:C29, "Must-Have") | C15: =SUMIFS('Equipment Quotation'!F5:F29, 'Equipment Quotation'!A5:A29, A15, 'Equipment Quotation'!C5:C29, "Secondary") | D15: =SUM(B15:C15)
A16: Startup Vehicle & Training Assets | B16: =SUMIFS('Equipment Quotation'!F5:F29, 'Equipment Quotation'!A5:A29, A16, 'Equipment Quotation'!C5:C29, "Must-Have") | C16: =SUMIFS('Equipment Quotation'!F5:F29, 'Equipment Quotation'!A5:A29, A16, 'Equipment Quotation'!C5:C29, "Secondary") | D16: =SUM(B16:C16)
A17: Total Category Sum | B17: =SUM(B11:B16) | C17: =SUM(C11:C16) | D17: =SUM(D11:D16)
